stoke/__init__.py
stoke/_version.py
stoke/configs.py
stoke/data.py
stoke/distributed.py
stoke/extensions.py
stoke/fp16.py
stoke/io_ops.py
stoke/status.py
stoke/stoke.py
stoke/utils.py
stoke-0.2.1.dist-info/LICENSE.txt
stoke-0.2.1.dist-info/METADATA
stoke-0.2.1.dist-info/NOTICE.txt
stoke-0.2.1.dist-info/WHEEL
stoke-0.2.1.dist-info/top_level.txt
stoke-0.2.1.dist-info/RECORD
